COPYING
MANIFEST.in
README.rst
setup.py
PySixel.egg-info/PKG-INFO
PySixel.egg-info/SOURCES.txt
PySixel.egg-info/dependency_links.txt
PySixel.egg-info/eager_resources.txt
PySixel.egg-info/entry_points.txt
PySixel.egg-info/not-zip-safe
PySixel.egg-info/requires.txt
PySixel.egg-info/top_level.txt
sixel/__init__.py
sixel/cellsize.py
sixel/converter.py
sixel/sixel.py
sixel/sixel_cimpl.c