Metadata-Version: 1.1
Name: PySixel
Version: 0.1.11
Summary: View full-pixel color graphics on SIXEL-supported terminals(xterm/mlterm/DECterm/Reflection/RLogin/tanasinn/yaft)
Home-page: https://github.com/saitoha/PySixel
Author: Hayaki Saito (user@zuse.jp)
Author-email: user@zuse.jp
License: GPL v3
Keywords: sixel terminal image
Platform: UNKNOWN
Classifier: Development Status :: 4 - Beta
Classifier: Topic :: Terminals
Classifier: Environment :: Console
Classifier: Intended Audience :: End Users/Desktop
Classifier: License :: OSI Approved :: GNU General Public License (GPL)
Classifier: Programming Language :: Python
